sapl_django/__init__.py
sapl_django/django_authorization_subscription_factory.py
sapl_django/django_streaming_policy_enforcement_point.py
sapl_django/sapl_request_middleware.py
sapl_django/templatetags/__init__.py
sapl_django/templatetags/sapl_extras.py
SAPL_Django-0.3.6.dist-info/LICENSE
SAPL_Django-0.3.6.dist-info/METADATA
SAPL_Django-0.3.6.dist-info/WHEEL
SAPL_Django-0.3.6.dist-info/top_level.txt
SAPL_Django-0.3.6.dist-info/RECORD
