Metadata-Version: 2.1
Name: SAPL-Django
Version: 0.3.6
Summary: initial upload to register the name for future development
Author-email: Dominic Heutelbeck <dominic@heutelbeck.com>
License: Copyright 2017-2022 Dominic Heutelbeck
License-File: LICENSE
Requires-Dist: django
Requires-Dist: channels
Requires-Dist: sapl-base
